twodify/__init__.py
twodify/__main__.py
twodify/twodimensional_plot.py
2dify-1.0.1.dist-info/METADATA
2dify-1.0.1.dist-info/WHEEL
2dify-1.0.1.dist-info/entry_points.txt
2dify-1.0.1.dist-info/top_level.txt
2dify-1.0.1.dist-info/RECORD
